setup.py
ldayelpchallenge/LDAsetup.py
ldayelpchallenge/__init__.py
ldayelpchallenge/anticontract.py
ldayelpchallenge/filter_lang.py
ldayelpchallenge/get_threshhold.py
ldayelpchallenge/ldamodelwrapper.py
ldayelpchallenge/math_helper.py
ldayelpchallenge/recommender.py
ldayelpchallenge/sortbyusers.py
ldayelpchallenge.egg-info/PKG-INFO
ldayelpchallenge.egg-info/SOURCES.txt
ldayelpchallenge.egg-info/dependency_links.txt
ldayelpchallenge.egg-info/not-zip-safe
ldayelpchallenge.egg-info/pbr.json
ldayelpchallenge.egg-info/requires.txt
ldayelpchallenge.egg-info/top_level.txt