Metadata-Version: 1.1
Name: ldayelpchallenge
Version: 0.1
Summary: Run Latent Dirichlet Allocation on the reviews provided by Yelp for the Yelp data challenge
Home-page: https://github.com/koschr/ldaforyelpchallenge
Author: CK
Author-email: test@example.com
License: MIT
Download-URL: https://github.com/koschr/ldaforyelpchallenge/tarball/1.0
Platform: UNKNOWN
